termis/__init__.py
termis/termis.py
termis/cli/__init__.py
termis/cli/parser.py
termis/cli/wizard.py
termis/config/__init__.py
termis/config/config_loader.py
termis/core/__init__.py
termis/core/command_executor.py
termis/core/iterm_manager.py
termis/core/termis_app.py
termis/exceptions/__init__.py
termis/exceptions/termis_exceptions.py
termis/integrations/__init__.py
termis/integrations/docker.py
termis/integrations/git.py
termis/integrations/tool_base.py
termis/integrations/tools_coordinator.py
termis/integrations/vscode.py
termis/utils/__init__.py
termis/utils/constants.py
termis/utils/profile_manager.py
termis-0.5.3.dist-info/METADATA
termis-0.5.3.dist-info/WHEEL
termis-0.5.3.dist-info/entry_points.txt
termis-0.5.3.dist-info/top_level.txt
termis-0.5.3.dist-info/RECORD
