Metadata-Version: 2.4
Name: termis
Version: 0.5.3
Summary: Snap your setup into place by automating your iTerm layouts and workflows
Home-page: https://github.com/smithg09/termis
Author: Smith Gajjar
Author-email: smith.gajjar@gmail.com
License: MIT
Classifier: Programming Language :: Python :: 3
Classifier: License :: OSI Approved :: MIT License
Classifier: Operating System :: MacOS
Classifier: Environment :: Console
Classifier: Intended Audience :: Developers
Classifier: Topic :: Terminals :: Terminal Emulators/X Terminals
Requires-Python: >=3.7.0
Requires-Dist: iterm2>=1.1
Requires-Dist: PyYAML>=5.3.1
Dynamic: author
Dynamic: author-email
Dynamic: classifier
Dynamic: description
Dynamic: description-content-type
Dynamic: home-page
Dynamic: license
Dynamic: requires-dist
Dynamic: requires-python
Dynamic: summary
